MANIFEST.in
README.md
setup.py
NP6HelperConfig/__init__.py
NP6HelperConfig/helperConfig.py
NP6HelperConfig.egg-info/PKG-INFO
NP6HelperConfig.egg-info/SOURCES.txt
NP6HelperConfig.egg-info/dependency_links.txt
NP6HelperConfig.egg-info/not-zip-safe
NP6HelperConfig.egg-info/top_level.txt