Metadata-Version: 1.0
Name: NP6HelperConfig
Version: 0.2
Summary: get informations present on the config.ini or in an other file formated for a configparser
Home-page: https://github.com/NP6/Python
Author: NP6 -SpaghetTeam
Author-email: fpi@np6.com
License: CC Licence
Keywords: configparser informations configuration config NP6
Platform: UNKNOWN
